fabled_rest/__init__.py
fabled_rest/cli.py
fabled_rest/fabled_rest.py
fabled_rest/handlers/__init__.py
fabled_rest/handlers/endpoints.py
fabled_rest/handlers/errors.py
fabled_rest/local/__init__.py
fabled_rest/local/progress/__init__.py
fabled_rest/local/progress/bar.py
fabled_rest/local/progress/counter.py
fabled_rest/local/progress/spinner.py
fabled_rest-0.2.2.dist-info/AUTHORS.rst
fabled_rest-0.2.2.dist-info/LICENSE
fabled_rest-0.2.2.dist-info/METADATA
fabled_rest-0.2.2.dist-info/WHEEL
fabled_rest-0.2.2.dist-info/entry_points.txt
fabled_rest-0.2.2.dist-info/top_level.txt
fabled_rest-0.2.2.dist-info/RECORD
