Metadata-Version: 2.1
Name: fabled-rest
Version: 0.2.2
Summary: Package designed to make creating API SDKs easier.
Home-page: https://github.com/zpyoung/fabled_rest
Author: Zachary Young
Author-email: solve@fabled.dev
License: MIT license
Keywords: fabled_rest
Platform: UNKNOWN
Classifier: Development Status :: 2 - Pre-Alpha
Classifier: Intended Audience :: Developers
Classifier: License :: OSI Approved :: MIT License
Classifier: Natural Language :: English
Classifier: Programming Language :: Python :: 3.7
Requires-Python: >=2.7, !=3.0.*, !=3.1.*, !=3.2.*, !=3.3.*, !=3.4.*
Requires-Dist: Click (>=7.0)
Requires-Dist: requests (>=2.22.0)
Requires-Dist: tqdm (==4.36.1)
